configstacker/__init__.py
configstacker/converters.py
configstacker/strategies.py
configstacker/utils.py
configstacker/sources/__init__.py
configstacker/sources/base.py
configstacker/sources/dictsource.py
configstacker/sources/environment.py
configstacker/sources/inifile.py
configstacker/sources/jsonfile.py
configstacker/sources/stacker.py
configstacker/sources/yamlfile.py
configstacker-0.2.0.dist-info/LICENSE
configstacker-0.2.0.dist-info/METADATA
configstacker-0.2.0.dist-info/WHEEL
configstacker-0.2.0.dist-info/top_level.txt
configstacker-0.2.0.dist-info/RECORD
