Metadata-Version: 2.1
Name: configstacker
Version: 0.2.0
Summary: Aggregates multiple configuration sources into one configuration object with dot-notation or dictionary-like access.
Home-page: https://gitlab.com/hakkropolis/configstacker
Author: Philipp Busch
Author-email: hakkeroid@philippbusch.de
License: BSD-3-clause
Project-URL: Bug Tracker, https://gitlab.com/hakkropolis/configstacker/issues
Project-URL: Documentation, https://configstacker.readthedocs.io
Project-URL: Source Code, https://gitlab.com/hakkropolis/configstacker/
Keywords: configuration hierarchy multi stacked configs
Platform: UNKNOWN
Classifier: Development Status :: 4 - Beta
Classifier: Intended Audience :: Developers
Classifier: License :: OSI Approved :: BSD License
Classifier: Natural Language :: English
Classifier: Operating System :: OS Independent
Classifier: Programming Language :: Python :: 2
Classifier: Programming Language :: Python :: 2.7
Classifier: Programming Language :: Python :: 3
Classifier: Programming Language :: Python :: 3.4
Classifier: Programming Language :: Python :: 3.5
Classifier: Programming Language :: Python :: 3.6
Classifier: Programming Language :: Python :: 3.7
Classifier: Topic :: Software Development :: Libraries
Requires-Python: >=2.7,!=3.0.*,!=3.1.*,!=3.2.*,!=3.3.*
Requires-Dist: six
Provides-Extra: yaml
Requires-Dist: pyyaml ; extra == 'yaml'
